<annotation>
    <filename>20220518-201030.jpg</filename>
    <folder>annotation</folder>
    <source>
        <database>annotation</database>
        <annotation>custom</annotation>
        <image>custom</image>
    </source>
    <size>
        <width>1280</width>
        <height>720</height>
        <depth>3</depth>
    </size>
    <segmented>0</segmented>
    <object>
        <name>ball</name>
        <pose>unspecified</pose>
        <truncated>0</truncated>
        <difficult>0</difficult>
        <bndbox>
            <xmin>373</xmin>
            <ymin>192</ymin>
            <xmax>467</xmax>
            <ymax>284</ymax>
        </bndbox>
    </object>
    <object>
        <name>goal</name>
        <pose>unspecified</pose>
        <truncated>0</truncated>
        <difficult>0</difficult>
        <bndbox>
            <xmin>587</xmin>
            <ymin>5</ymin>
            <xmax>1005</xmax>
            <ymax>262</ymax>
        </bndbox>
    </object>
</annotation>
